fast_point_api/__init__.py
fast_point_api/app_factory.py
fast_point_api/config.py
fast_point_api/crud.py
fast_point_api/endpoints.py
fast_point_api/models.py
fast_point_api/schemas.py
fast_point_api/utils.py
fast_point_api/db_managers/__init__.py
fast_point_api/db_managers/couchdb_manager.py
fast_point_api/db_managers/mongo_manager.py
fast_point_api/db_managers/postgres_manager.py
fast_point_api-1.0.0.dist-info/LICENSE
fast_point_api-1.0.0.dist-info/METADATA
fast_point_api-1.0.0.dist-info/WHEEL
fast_point_api-1.0.0.dist-info/top_level.txt
fast_point_api-1.0.0.dist-info/RECORD
