Metadata-Version: 2.1
Name: fast-point-api
Version: 1.0.0
Summary: A package for building APIs with FastAPI, providing integration with CouchDB for managing collections and CRUD operations.
Home-page: https://github.com/UPT-FAING-EPIS/proyecto-si8811a-2024-ii-u2-api-y-funciones-anahua
Author: maynerac
Author-email: mayneranahuacoaquira@gmail.com
License: MIT
Classifier: Development Status :: 4 - Beta
Classifier: Programming Language :: Python :: 3.12
Classifier: Framework :: FastAPI
Classifier: License :: OSI Approved :: MIT License
Requires-Python: >=3.12
License-File: LICENSE
Requires-Dist: annotated-types==0.7.0
Requires-Dist: anyio==4.4.0
Requires-Dist: click==8.1.7
Requires-Dist: colorama==0.4.6
Requires-Dist: CouchDB==1.2
Requires-Dist: fastapi==0.114.0
Requires-Dist: h11==0.14.0
Requires-Dist: idna==3.8
Requires-Dist: pydantic==2.9.0
Requires-Dist: pydantic_core==2.23.2
Requires-Dist: sniffio==1.3.1
Requires-Dist: starlette==0.38.4
Requires-Dist: typing_extensions==4.12.2
Requires-Dist: tzdata==2024.1
Requires-Dist: uvicorn==0.30.6
